mAdvisor/AutoML.cp38-win_amd64.pyd
mAdvisor/__init__.py
mAdvisor/version.cp38-win_amd64.pyd
mAdvisor/bi/__init__.py
mAdvisor/bi/autoconfig.cp38-win_amd64.pyd
mAdvisor/bi/crud.cp38-win_amd64.pyd
mAdvisor/bi/database.cp38-win_amd64.pyd
mAdvisor/bi/master.cp38-win_amd64.pyd
mAdvisor/bi/master_helper.cp38-win_amd64.pyd
mAdvisor/bi/models.cp38-win_amd64.pyd
mAdvisor/bi/preprocessing.cp38-win_amd64.pyd
mAdvisor/bi/schemas.py
mAdvisor/bi/validator.py
mAdvisor/bi/admin/__init__.py
mAdvisor/bi/admin/auth.cp38-win_amd64.pyd
mAdvisor/bi/admin/plan.cp38-win_amd64.pyd
mAdvisor/bi/algorithms/__init__.py
mAdvisor/bi/algorithms/decision_tree.cp38-win_amd64.pyd
mAdvisor/bi/algorithms/decision_tree_regression.cp38-win_amd64.pyd
mAdvisor/bi/algorithms/gain_lift_ks.cp38-win_amd64.pyd
mAdvisor/bi/algorithms/linear_regression.cp38-win_amd64.pyd
mAdvisor/bi/algorithms/nnpt_utils.cp38-win_amd64.pyd
mAdvisor/bi/algorithms/pyTorch.cp38-win_amd64.pyd
mAdvisor/bi/algorithms/time_series_forecasting.cp38-win_amd64.pyd
mAdvisor/bi/algorithms/utils.cp38-win_amd64.pyd
mAdvisor/bi/algorithms/autoML/Data_Preprocessing.cp38-win_amd64.pyd
mAdvisor/bi/algorithms/autoML/Feature_Engineering.cp38-win_amd64.pyd
mAdvisor/bi/algorithms/autoML/Sampling.cp38-win_amd64.pyd
mAdvisor/bi/algorithms/autoML/__init__.py
mAdvisor/bi/algorithms/autoML/auto_ml.cp38-win_amd64.pyd
mAdvisor/bi/algorithms/autoML/auto_ml_master.cp38-win_amd64.pyd
mAdvisor/bi/algorithms/autoML/auto_ml_score.cp38-win_amd64.pyd
mAdvisor/bi/algorithms/autoML/auto_ml_score1.cp38-win_amd64.pyd
mAdvisor/bi/algorithms/autoML/data_preprocessing_auto_ml.cp38-win_amd64.pyd
mAdvisor/bi/algorithms/autoML/data_validation.cp38-win_amd64.pyd
mAdvisor/bi/algorithms/autoML/feature_engineering_auto_ml.cp38-win_amd64.pyd
mAdvisor/bi/algorithms/autoML/feature_selection.cp38-win_amd64.pyd
mAdvisor/bi/algorithms/autoML/utils_automl.cp38-win_amd64.pyd
mAdvisor/bi/common/__init__.py
mAdvisor/bi/common/algorithmSetting.cp38-win_amd64.pyd
mAdvisor-0.3.6.dist-info/METADATA
mAdvisor-0.3.6.dist-info/WHEEL
mAdvisor-0.3.6.dist-info/top_level.txt
mAdvisor-0.3.6.dist-info/RECORD
