Metadata-Version: 2.1
Name: mAdvisor
Version: 0.3.6
Summary: An automated AI/ML solution from Marlabs
Home-page: https://www.marlabs.com/platforms/cognitive-computing-AI-ML-platform/
Author: Marlabs Inc.
Author-email: mAdvisor_AutoML@marlabs.com
Maintainer: Rahul Sivankutty
Maintainer-email: Rahul.Sivankutty@marlabs.com
License: UNKNOWN
Keywords: machine learning,data science,automated machine learning,regressor,regressors,regression,classification,classifiers,classifier,estimators,predictors,XGBoost,Random Forest,sklearn,scikit-learn,analytics,analysts,feature importancesanalytics,artificial intelligence,ensembling,feature engineering,feature extraction,feature selection,production,pandas,dataframes,deep learning,tensorflow,deeplearning,lightgbm,gradient boosting,gbm,keras,production ready
Platform: UNKNOWN
Classifier: Programming Language :: Python :: 3
Classifier: Programming Language :: Python :: 3.6
Classifier: Programming Language :: Python :: 3.7
Classifier: Programming Language :: Python :: 3.8
Classifier: License :: OSI Approved :: MIT License
Classifier: Operating System :: POSIX :: Linux
Classifier: Operating System :: Microsoft :: Windows
Classifier: Topic :: Scientific/Engineering :: Artificial Intelligence
Classifier: Topic :: Scientific/Engineering :: Information Analysis
Classifier: Topic :: Software Development :: Libraries :: Python Modules
Requires-Python: >=3.6
Requires-Dist: cryptography (==2.8)
Requires-Dist: DateTime (==4.3)
Requires-Dist: future (==0.17.1)
Requires-Dist: humanize (==0.5.1)
Requires-Dist: imbalanced-learn (==0.6.1)
Requires-Dist: imblearn (==0.0)
Requires-Dist: Jinja2 (==2.10)
Requires-Dist: joblib (==0.16.0)
Requires-Dist: lightgbm (==2.3.1)
Requires-Dist: matplotlib (==3.3.4)
Requires-Dist: mlxtend (==0.17.2)
Requires-Dist: numpy (==1.19.5)
Requires-Dist: pandas (==1.1.5)
Requires-Dist: Pint (==0.10.1)
Requires-Dist: pyspark (==3.0.2)
Requires-Dist: requests (==2.25.1)
Requires-Dist: sklearn2pmml (==0.65.0)
Requires-Dist: statsmodels (==0.12.1)
Requires-Dist: tensorflow (==2.4.1)
Requires-Dist: uuid (==1.30)
Requires-Dist: validate-email (==1.3)
Requires-Dist: xgboost (==0.82)
Requires-Dist: scipy (==1.4.1)
Requires-Dist: torchvision (==0.9.0)
Requires-Dist: scikit-learn (==0.23.2)
Requires-Dist: pyenchant (==3.2.0)
Requires-Dist: SQLAlchemy (==1.3.17)
Requires-Dist: psycopg2-binary (==2.8.5)
Requires-Dist: pydantic (==1.7.3)
